mega/__init__.py
mega/api.py
mega/client.py
mega/crypto.py
mega/data_structures.py
mega/errors.py
mega/main.py
mega/xhashcash.py
async_mega_py-1.10.2.post0.dist-info/licenses/LICENSE
async_mega_py-1.10.2.post0.dist-info/WHEEL
async_mega_py-1.10.2.post0.dist-info/entry_points.txt
async_mega_py-1.10.2.post0.dist-info/METADATA
async_mega_py-1.10.2.post0.dist-info/RECORD
