Metadata-Version: 2.4
Name: async-mega-py
Version: 1.10.2.post0
Summary: Python lib for the Mega.co.nz API.
Author: O'Dwyer Software
Author-email: O'Dwyer Software <hello@odwyer.software>
License-Expression: Apache-2.0
License-File: LICENSE
Requires-Dist: aiohttp>=3.11.18
Requires-Dist: pycryptodome==3.19.0
Requires-Dist: rich>=13.0.0
Requires-Dist: tenacity>=9.0.0
Maintainer: NTFSvolume
Requires-Python: >=3.10
Project-URL: Homepage, https://github.com/NTFSvolume/mega.py
